{
"type": "FeatureCollection",
"name": "Ancient Cross",
"crs": { "type": "name", "properties": { "name": "urn:ogc:def:crs:OGC:1.3:CRS84" } },
"features": [
{ "type": "Feature", "properties": { "Name": "Steinkreuz Haggenegg", "description": "\n        <b>Type:<\/b> Ancient Cross <b>County\/Region:<\/b> Schwyz <b>Alt Name:<\/b> Steinkreuz Pilgerkapelle <br \/> Pos Accuracy: <b>5<\/b> Condition: <b>5<\/b> (5 is best)   Ambience: <b>4<\/b>  Access: <b>4<\/b>  (5 is best)<br \/>\n                    <b>Lat:<\/b> 47.05141 &nbsp;&nbsp;&nbsp;<b>Long<\/b>: 8.68426<img src=\"http:\/\/www.megalithic.co.uk\/a558\/a312\/gallery\/Central_Europe\/Switzerland\/thumb\/20230610130515_IMG_7140.jpg\" align=\"right\" valign=\"top\"><\/a>\n<br \/>\n                    Ancient Cross in Schwyz. Stone cross from the 14th or 15th Century. It was excavated here around 1700. A chapel was built above it. In 2010 the chapel was renovated and the cross now has a dignified p...<b>.<\/b> (c) Meg. Portal contributors.<br \/>\n\t\t     <a href=\"http:\/\/www.megalithic.co.uk\/article.php?sid=58199\" >Link To More Information<\/a><br \/>\n                    " }, "geometry": { "type": "Point", "coordinates": [ 8.68426, 47.05141 ] } }
]
}
